flappybird/__init__.py
flappybird/__main__.py
flappybird/py.typed
flappybird/assets/bird.png
flappybird/assets/bottom_pipe.png
flappybird/assets/top_pipe.png
flappybird-0.2.1.dist-info/LICENSE
flappybird-0.2.1.dist-info/METADATA
flappybird-0.2.1.dist-info/WHEEL
flappybird-0.2.1.dist-info/entry_points.txt
flappybird-0.2.1.dist-info/top_level.txt
flappybird-0.2.1.dist-info/RECORD
